TAssist/TA_Globals.py
TAssist/TA_Graphs.py
TAssist/TAssist.py
TAssist/__init__.py
TAssist-0.0.4.dist-info/METADATA
TAssist-0.0.4.dist-info/WHEEL
TAssist-0.0.4.dist-info/top_level.txt
TAssist-0.0.4.dist-info/RECORD
