Metadata-Version: 2.1
Name: TAssist
Version: 0.0.4
Summary: An unnoficial python wrapper for the TA Public API (2.0) by Pegasis
Home-page: UNKNOWN
Author: BearGaming123 (Supreeth Govindaraju)
Author-email: <supreethG@gmx.com>
License: UNKNOWN
Keywords: python,Teach Assist,YRDSB
Platform: UNKNOWN
Classifier: Development Status :: 1 - Planning
Classifier: Intended Audience :: Developers
Classifier: Programming Language :: Python :: 3
Classifier: Operating System :: Microsoft :: Windows
Requires-Dist: numpy
Requires-Dist: matplotlib
Requires-Dist: requests
